ns1cli/__init__.py
ns1cli/cli.py
ns1cli/repl.py
ns1cli/util.py
ns1cli/commands/__init__.py
ns1cli/commands/cmd_config.py
ns1cli/commands/cmd_data.py
ns1cli/commands/cmd_monitor.py
ns1cli/commands/cmd_record.py
ns1cli/commands/cmd_stats.py
ns1cli/commands/cmd_zone.py
ns1cli-0.9.2.dist-info/DESCRIPTION.rst
ns1cli-0.9.2.dist-info/METADATA
ns1cli-0.9.2.dist-info/RECORD
ns1cli-0.9.2.dist-info/WHEEL
ns1cli-0.9.2.dist-info/entry_points.txt
ns1cli-0.9.2.dist-info/metadata.json
ns1cli-0.9.2.dist-info/top_level.txt
